fbmc_quality/__init__.py
fbmc_quality/dataframe_schemas/__init__.py
fbmc_quality/dataframe_schemas/cache_db/__init__.py
fbmc_quality/dataframe_schemas/cache_db/cache_db_functions.py
fbmc_quality/dataframe_schemas/schemas.py
fbmc_quality/datetime_handlers/handle_timezones.py
fbmc_quality/entsoe_data/__init__.py
fbmc_quality/entsoe_data/entsoe_store_cli.py
fbmc_quality/entsoe_data/fetch_entsoe_data.py
fbmc_quality/enums/__init__.py
fbmc_quality/enums/bidding_zones.py
fbmc_quality/exceptions/fbmc_exceptions.py
fbmc_quality/jao_data/__init__.py
fbmc_quality/jao_data/analyse_jao_data.py
fbmc_quality/jao_data/fetch_jao_data.py
fbmc_quality/jao_data/jao_store_cli.py
fbmc_quality/linearisation_analysis/__init__.py
fbmc_quality/linearisation_analysis/compute_functions.py
fbmc_quality/linearisation_analysis/dataclasses.py
fbmc_quality/linearisation_analysis/process_data.py
fbmc_quality/linearisation_error_app/__init__.py
fbmc_quality/linearisation_error_app/basic_app.py
fbmc_quality/plotting/__init__.py
fbmc_quality/plotting/flow_map.py
fbmc_linearisation_analysis-0.4.4.dist-info/LICENSE
fbmc_linearisation_analysis-0.4.4.dist-info/METADATA
fbmc_linearisation_analysis-0.4.4.dist-info/WHEEL
fbmc_linearisation_analysis-0.4.4.dist-info/entry_points.txt
fbmc_linearisation_analysis-0.4.4.dist-info/RECORD
