Metadata-Version: 2.1
Name: fbmc-linearisation-analysis
Version: 0.4.4
Summary: 
Author: Robert Solli
Author-email: robert@xal.no
Requires-Python: >=3.10, !=2.7.*, !=3.0.*, !=3.1.*, !=3.2.*, !=3.3.*, !=3.4.*, !=3.5.*, !=3.6.*, !=3.7.*, !=3.8.*, !=3.9.*
Classifier: Programming Language :: Python :: 3
Classifier: Programming Language :: Python :: 3.10
Classifier: Programming Language :: Python :: 3.12
Provides-Extra: all
Provides-Extra: app-template
Provides-Extra: plotting
Requires-Dist: aiohttp (>=3.8.5,<4.0.0)
Requires-Dist: beautifulsoup4 (>=4.12.2,<5.0.0)
Requires-Dist: cache_to_disk
Requires-Dist: duckdb (==0.10.2)
Requires-Dist: duckdb-engine (>=0.9.2,<0.10.0)
Requires-Dist: entsoe-py (>=0.6.2)
Requires-Dist: geojson-rewind ; extra == "app-template" or extra == "plotting" or extra == "all"
Requires-Dist: geopandas ; extra == "app-template" or extra == "plotting" or extra == "all"
Requires-Dist: levenshtein (>=0.22.0,<0.23.0)
Requires-Dist: matplotlib (>=3.7.2,<4.0.0)
Requires-Dist: pandas (>=2.1.0,<3.0.0)
Requires-Dist: pandera[mypy] (>=0.17.0,<0.18.0)
Requires-Dist: pillow ; extra == "app-template" or extra == "plotting" or extra == "all"
Requires-Dist: plotly (>=5.17.0,<6.0.0) ; extra == "app-template" or extra == "plotting" or extra == "all"
Requires-Dist: polars (>=0.20.3,<0.21.0)
Requires-Dist: pyarrow (==16.1.0)
Requires-Dist: pytz (>=2023.3,<2024.0)
Requires-Dist: requests (>=2.31.0,<3.0.0)
Requires-Dist: scikit-learn (>=1.3.0,<2.0.0)
Requires-Dist: shapely ; extra == "app-template" or extra == "plotting" or extra == "all"
Requires-Dist: streamlit (>=1.27.1,<2.0.0) ; extra == "app-template" or extra == "all"
Requires-Dist: typer[all] (>=0.9.0,<0.10.0)
Requires-Dist: tzlocal (>=5.0.1,<6.0.0)
